README.rst
setup.py
WAVfilter/WAVFilterBase.py
WAVfilter/__init__.py
WAVfilter/butter.py
butterworth/__init__.py
butterworth/butter.py
butterworth.egg-info/PKG-INFO
butterworth.egg-info/SOURCES.txt
butterworth.egg-info/dependency_links.txt
butterworth.egg-info/requires.txt
butterworth.egg-info/top_level.txt
filters/__init__.py
filters/butterbase.py
filters/butterbase0.py
filters/butterbase2.py
filters/butterbase3.py
filters/butterworth.py