Metadata-Version: 1.1
Name: butterworth
Version: 0.0.1
Summary: Real-time digital butterworth IIR filter
Home-page: https://github.com/keikun555/butter
Author: Kei Imada
Author-email: kimada1@swarthmore.edu
License: MIT
Keywords: signal processing butterworth filter IIR infinite impulse response forward-backward filtering
Platform: UNKNOWN
Classifier: Development Status :: 4 - Beta
Classifier: Intended Audience :: Science/Research
Classifier: Topic :: Scientific/Engineering
Classifier: License :: OSI Approved :: MIT License
Classifier: Programming Language :: Python :: 2
Classifier: Programming Language :: Python :: 2.7
